nnja_ai/__init__.py
nnja_ai/catalog.py
nnja_ai/dataset.py
nnja_ai/exceptions.py
nnja_ai/io.py
nnja_ai/variable.py
nnja_ai/schemas/catalog_schema_v1.json
nnja_ai/schemas/dataset_schema_v1.json
nnja_ai-1.0.0.dist-info/licenses/LICENSE
nnja_ai-1.0.0.dist-info/METADATA
nnja_ai-1.0.0.dist-info/WHEEL
nnja_ai-1.0.0.dist-info/top_level.txt
nnja_ai-1.0.0.dist-info/RECORD
