Metadata-Version: 2.4
Name: nnja-ai
Version: 1.0.0
Summary: Find and load data from the Brightband AI-ready mirror of the NOAA NASA Joint Archive (NNJA) of Observations for Earth System Reanalysis
License: MIT License
Project-URL: Documentation, https://nnja-ai.readthedocs.io/
Project-URL: Repository, https://github.com/brightbandtech/nnja-ai
Keywords: NNJA,artificial intelligence,earth system reanalysis,data catalog,dataset,earth observation
Classifier: Intended Audience :: Science/Research
Classifier: License :: OSI Approved :: MIT License
Classifier: Operating System :: OS Independent
Classifier: Programming Language :: Python :: 3
Classifier: Programming Language :: Python :: 3.10
Classifier: Programming Language :: Python :: 3.11
Classifier: Topic :: Scientific/Engineering :: Atmospheric Science
Requires-Python: >=3.10
License-File: LICENSE
Requires-Dist: fsspec>=2024.10.0
Requires-Dist: gcsfs>=2024.10.0
Requires-Dist: google-auth>=2.36.0
Requires-Dist: jsonschema>=4.23.0
Requires-Dist: pandas>=2.2.3
Requires-Dist: parquet>=1.3.1
Requires-Dist: pyarrow>=18.1.0
Provides-Extra: interactive
Requires-Dist: ipykernel; extra == "interactive"
Requires-Dist: jupyterlab; extra == "interactive"
Requires-Dist: matplotlib; extra == "interactive"
Provides-Extra: dask
Requires-Dist: dask[dataframe]>=2024.12.0; extra == "dask"
Provides-Extra: polars
Requires-Dist: polars>=1.17.1; extra == "polars"
Provides-Extra: complete
Requires-Dist: nnja-ai[dask,interactive,polars]; extra == "complete"
Dynamic: license-file
